{
  "total_references": 56,
  "year_range": {
    "min": 1966,
    "max": 2025,
    "median": 2022
  },
  "year_distribution": {
    "1966": 1,
    "1988": 1,
    "1997": 1,
    "2004": 1,
    "2013": 1,
    "2016": 3,
    "2017": 2,
    "2018": 4,
    "2019": 3,
    "2020": 4,
    "2021": 4,
    "2022": 5,
    "2023": 10,
    "2024": 13,
    "2025": 3
  },
  "entry_type_distribution": {
    "article": 22,
    "misc": 18,
    "inproceedings": 12,
    "techreport": 3,
    "book": 1
  },
  "top_venues": {
    "Advances in Neural Information Processing Systems": 4,
    "Journal of Machine Learning Research": 2,
    "Proceedings of the AAAI Conference on Artificial Intelligence": 2,
    "Science": 2,
    "arXiv preprint": 2,
    "Journal of Artificial Intelligence Research": 1,
    "Proceedings of the 2019 Conference of the North American Chapter of the Association for Computational Linguistics": 1,
    "Nature": 1,
    "World Wide Web Consortium": 1,
    "The VLDB Journal": 1,
    "IEEE Data Engineering Bulletin": 1,
    "Proceedings of the ACL-04 Workshop on Text Summarization Branches Out": 1,
    "Soviet Physics Doklady": 1,
    "AI Magazine": 1,
    "Journal of Biomedical Semantics": 1
  },
  "recency_index": {
    "period": "2022-2025",
    "count": 31,
    "total_with_year": 56,
    "percentage": 55.4
  }
}
